{"mean":{"confidence_interval":{"confidence_level":0.95,"lower_bound":982241.3176815222,"upper_bound":994170.1554023193},"point_estimate":986848.6991494574,"standard_error":3204.661780014842},"median":{"confidence_interval":{"confidence_level":0.95,"lower_bound":979876.0537530266,"upper_bound":983031.7011494252},"point_estimate":981412.0776512236,"standard_error":894.2904752518868},"median_abs_dev":{"confidence_interval":{"confidence_level":0.95,"lower_bound":4745.952229271796,"upper_bound":8494.813945020258},"point_estimate":7184.635579683995,"standard_error":977.9587838060103},"slope":{"confidence_interval":{"confidence_level":0.95,"lower_bound":978817.0706121037,"upper_bound":981065.2808787792},"point_estimate":979928.6890764001,"standard_error":575.591846957545},"std_dev":{"confidence_interval":{"confidence_level":0.95,"lower_bound":8567.274869214169,"upper_bound":53323.44630814248},"point_estimate":32194.02178967561,"standard_error":14978.430381455526}}